datatools.py
fmn_plottools.py
pyquac/__init__.py
pyquac/datatools.py
pyquac/fmn_datatools.py
pyquac/fmn_datatools_v0.py
pyquac/fmn_datatools_v2.py
pyquac/fmn_plottools.py
pyquac/fmn_spectroscopy.py
pyquac/fmn_tts.py
src/__init__.py
src/datatools.py
src/fmn_plottools.py
pyquac-1.1.11.dist-info/LICENSE.txt
pyquac-1.1.11.dist-info/METADATA
pyquac-1.1.11.dist-info/WHEEL
pyquac-1.1.11.dist-info/top_level.txt
pyquac-1.1.11.dist-info/RECORD
