Metadata-Version: 2.1
Name: pyquac
Version: 1.1.11
Summary: Useful tools for quantum computing experiments, provided for BMSTU FMN
Home-page: https://github.com/ikaryss/pyquac
Author: Nikolay Zhitkov
Author-email: nokolay.zh@gmail.com
License: MIT
Download-URL: https://pypi.org/project/pyquac/
Keywords: Two tone spectroscopy,plotly,pandas
Platform: UNKNOWN
Classifier: Programming Language :: Python :: 3
Classifier: Programming Language :: Python :: 3.6
Classifier: Programming Language :: Python :: 3.7
Classifier: Programming Language :: Python :: 3.8
Classifier: Programming Language :: Python :: 3.9
Classifier: Programming Language :: Python :: 3.10
Classifier: Operating System :: OS Independent
License-File: LICENSE.txt
Requires-Dist: dash (>=1.21.0)
Requires-Dist: jupyter-dash (>=0.4.0)
Requires-Dist: numba (>=0.54.0)
Requires-Dist: kaleido (==0.1.0)
Requires-Dist: Pillow
